LICENSE
MANIFEST.in
README.md
setup.cfg
setup.py
graphene_chain_mutation/__init__.py
graphene_chain_mutation/mutations.py
graphene_chain_mutation.egg-info/PKG-INFO
graphene_chain_mutation.egg-info/SOURCES.txt
graphene_chain_mutation.egg-info/dependency_links.txt
graphene_chain_mutation.egg-info/requires.txt
graphene_chain_mutation.egg-info/top_level.txt
tests/__init__.py
tests/fake.py
tests/test.py