Metadata-Version: 2.1
Name: graphene-chain-mutation
Version: 1.1.0
Summary: Provide feature to reference previous mutations results in chained mutations.
Home-page: https://github.com/shinhermit/graphene-chain-mutation
Author: Josuah ARON
Author-email: josuah.aron@cogitans.fr
License: MIT
Platform: UNKNOWN
Classifier: Environment :: Web Environment
Classifier: Intended Audience :: Developers
Classifier: License :: OSI Approved :: MIT License
Classifier: Operating System :: OS Independent
Classifier: Programming Language :: Python
Classifier: Programming Language :: Python :: 3
Classifier: Programming Language :: Python :: 3 :: Only
Classifier: Programming Language :: Python :: 3.8
Classifier: Programming Language :: Python :: 3.9
Classifier: Programming Language :: Python :: 3.10
Classifier: Topic :: Internet :: WWW/HTTP
Classifier: Topic :: Internet :: WWW/HTTP :: Dynamic Content
License-File: LICENSE
